RobustGaussianFittingLibrary/RGFLib.c
RobustGaussianFittingLibrary/RGFLib.h
RobustGaussianFittingLibrary/RGFLib_mex_fitValue2Skewed.c
RobustGaussianFittingLibrary/RGFLib_mex_fitValue2Skewed_Test.m
RobustGaussianFittingLibrary/__init__.py
RobustGaussianFittingLibrary/basic.py
RobustGaussianFittingLibrary/cWrapper.py
RobustGaussianFittingLibrary/misc.py
RobustGaussianFittingLibrary/useMultiproc.py
RobustGaussianFittingLibrary-0.2.0.dist-info/LICENSE
RobustGaussianFittingLibrary-0.2.0.dist-info/METADATA
RobustGaussianFittingLibrary-0.2.0.dist-info/WHEEL
RobustGaussianFittingLibrary-0.2.0.dist-info/top_level.txt
RobustGaussianFittingLibrary-0.2.0.dist-info/RECORD
