Metadata-Version: 2.1
Name: RobustGaussianFittingLibrary
Version: 0.2.0
Summary: A library for robust Gaussian fitting of geometric models in presence of outliers. 
Home-page: https://github.com/arsadri/RobustGaussianFittingLibrary
Author: Alireza Sadri
Author-email: arsadri@gmail.com
License: MIT
Keywords: rgflib,outlier,outlier detection,outlier removal,anamoly detection,curve fitting,line fitting,plane fitting,fit a Gaussian,Gaussian fitting
Classifier: Development Status :: 3 - Alpha
Classifier: Intended Audience :: Science/Research
Classifier: Topic :: Scientific/Engineering :: Mathematics
Classifier: License :: OSI Approved :: MIT License
Classifier: Programming Language :: Python :: 3
Classifier: Programming Language :: Python :: 3.7
Classifier: Programming Language :: Python :: 3.8
Classifier: Programming Language :: Python :: 3.9
Classifier: Programming Language :: Python :: 3.10
Classifier: Programming Language :: Python :: 3.11
Requires-Python: >=3.6
License-File: LICENSE
Requires-Dist: numpy
Requires-Dist: scipy
Requires-Dist: matplotlib
Requires-Dist: lognflow
